pina/__init__.py
pina/enums.py
pina/heat_cascade.py
pina/pinch_analyzer.py
pina/stream.py
pina/segments/__init__.py
pina/segments/base_segment.py
pina/segments/latent_segment.py
pina/segments/sensible_segment.py
pina-0.1.1.dist-info/LICENSE
pina-0.1.1.dist-info/WHEEL
pina-0.1.1.dist-info/METADATA
pina-0.1.1.dist-info/RECORD
