Metadata-Version: 2.1
Name: pina
Version: 0.1.1
Summary: A lightweight pinch analysis package
Home-page: https://github.com/FitzOReilly/pina
License: UNKNOWN
Author: Patrick Heck
Author-email: fitz_oreilly@outlook.com
Requires-Python: >=3.6
Classifier: License :: OSI Approved :: MIT License
Requires-Dist: black ; extra == "dev"
Requires-Dist: coverage ; extra == "dev"
Requires-Dist: flake8 ; extra == "dev"
Requires-Dist: isort ; extra == "dev"
Requires-Dist: pre-commit ; extra == "dev"
Requires-Dist: tox ; extra == "dev"
Provides-Extra: dev
